malariagen_data/__init__.py
malariagen_data/adir1.py
malariagen_data/af1.py
malariagen_data/ag3.py
malariagen_data/amin1.py
malariagen_data/anoph/__init__.py
malariagen_data/anoph/aim_data.py
malariagen_data/anoph/aim_params.py
malariagen_data/anoph/base.py
malariagen_data/anoph/base_params.py
malariagen_data/anoph/clustering_params.py
malariagen_data/anoph/cnv_data.py
malariagen_data/anoph/cnv_frq.py
malariagen_data/anoph/cnv_params.py
malariagen_data/anoph/dash_params.py
malariagen_data/anoph/dipclust.py
malariagen_data/anoph/dipclust_params.py
malariagen_data/anoph/distance.py
malariagen_data/anoph/distance_params.py
malariagen_data/anoph/frq_base.py
malariagen_data/anoph/frq_params.py
malariagen_data/anoph/fst.py
malariagen_data/anoph/fst_params.py
malariagen_data/anoph/g123.py
malariagen_data/anoph/g123_params.py
malariagen_data/anoph/genome_features.py
malariagen_data/anoph/genome_sequence.py
malariagen_data/anoph/gplt_params.py
malariagen_data/anoph/h12.py
malariagen_data/anoph/h12_params.py
malariagen_data/anoph/h1x.py
malariagen_data/anoph/hap_data.py
malariagen_data/anoph/hap_frq.py
malariagen_data/anoph/hap_params.py
malariagen_data/anoph/hapclust.py
malariagen_data/anoph/hapclust_params.py
malariagen_data/anoph/hapnet_params.py
malariagen_data/anoph/het_params.py
malariagen_data/anoph/igv.py
malariagen_data/anoph/ihs_params.py
malariagen_data/anoph/karyotype.py
malariagen_data/anoph/karyotype_params.py
malariagen_data/anoph/map_params.py
malariagen_data/anoph/pca.py
malariagen_data/anoph/pca_params.py
malariagen_data/anoph/phenotype_params.py
malariagen_data/anoph/phenotypes.py
malariagen_data/anoph/plink_params.py
malariagen_data/anoph/plotly_params.py
malariagen_data/anoph/sample_metadata.py
malariagen_data/anoph/snp_data.py
malariagen_data/anoph/snp_frq.py
malariagen_data/anoph/to_plink.py
malariagen_data/anoph/tree_params.py
malariagen_data/anoph/xpehh_params.py
malariagen_data/anopheles.py
malariagen_data/mjn.py
malariagen_data/pf7.py
malariagen_data-15.6.0.dist-info/LICENSE
malariagen_data-15.6.0.dist-info/METADATA
malariagen_data-15.6.0.dist-info/WHEEL
malariagen_data-15.6.0.dist-info/RECORD
