Metadata-Version: 2.1
Name: malariagen_data
Version: 15.6.0
Summary: A package for accessing and analysing MalariaGEN data.
Home-page: https://github.com/malariagen/malariagen-data-python
License: MIT
Author: Alistair Miles
Author-email: alistair.miles@sanger.ac.uk
Requires-Python: >=3.10,<3.13
Classifier: License :: OSI Approved :: MIT License
Classifier: Programming Language :: Python :: 3
Classifier: Programming Language :: Python :: 3.10
Classifier: Programming Language :: Python :: 3.11
Classifier: Programming Language :: Python :: 3.12
Provides-Extra: dev
Requires-Dist: BioPython
Requires-Dist: anjl (>=1.2.0)
Requires-Dist: bed_reader
Requires-Dist: bokeh (<3.7.0)
Requires-Dist: dash (<3.0.0)
Requires-Dist: dash-cytoscape (>=1.0.0)
Requires-Dist: dask[array]
Requires-Dist: distributed
Requires-Dist: fsspec
Requires-Dist: gcsfs
Requires-Dist: google-auth
Requires-Dist: igv-notebook (>=0.2.3)
Requires-Dist: ipinfo (!=4.4.1)
Requires-Dist: ipyleaflet (>=0.17.0)
Requires-Dist: ipywidgets
Requires-Dist: jupyterlab ; extra == "dev"
Requires-Dist: llvmlite
Requires-Dist: memory-profiler ; extra == "dev"
Requires-Dist: mypy ; extra == "dev"
Requires-Dist: notebook ; extra == "dev"
Requires-Dist: numba (>=0.60.0)
Requires-Dist: numcodecs (<0.16)
Requires-Dist: numpy (<2.2)
Requires-Dist: numpydoc_decorator (>=2.1.0)
Requires-Dist: orjson
Requires-Dist: pandas
Requires-Dist: pandas-stubs ; extra == "dev"
Requires-Dist: plotly
Requires-Dist: pre-commit ; extra == "dev"
Requires-Dist: protopunica (>=0.14.8.post2)
Requires-Dist: pydata-sphinx-theme ; extra == "dev"
Requires-Dist: pytest ; extra == "dev"
Requires-Dist: pytest-cases ; extra == "dev"
Requires-Dist: pytest-cov ; extra == "dev"
Requires-Dist: pytest-mock
Requires-Dist: pytest-xdist ; extra == "dev"
Requires-Dist: ruff ; extra == "dev"
Requires-Dist: s3fs
Requires-Dist: scikit-allel (>=1.3.13)
Requires-Dist: scipy
Requires-Dist: snakeviz ; extra == "dev"
Requires-Dist: sphinx ; extra == "dev"
Requires-Dist: sphinx_design ; extra == "dev"
Requires-Dist: statsmodels
Requires-Dist: tqdm
Requires-Dist: typeguard (>=4.0.0)
Requires-Dist: typing_extensions
Requires-Dist: xarray
Requires-Dist: yaspin
Requires-Dist: zarr (>=2.11,<3.0.0)
Project-URL: Documentation, https://malariagen.github.io/malariagen-data-python/latest/
Project-URL: Repository, https://github.com/malariagen/malariagen-data-python
